[
  {
    "id": "1783176247000-20260704_2025szmap.webp",
    "filename": "20260704_2025szmap.webp",
    "url": "https://pico-beige.vercel.app/api/image?path=wallpaper/20260704_2025szmap.webp",
    "folder": "wallpaper",
    "time": "2026-07-04T22:44:07+08:00"
  },
  {
    "id": "1783166025000-20260704_ed32cv.jpg",
    "filename": "20260704_ed32cv.jpg",
    "url": "https://pico-beige.vercel.app/api/image?path=wallpaper/20260704_ed32cv.jpg",
    "folder": "wallpaper",
    "time": "2026-07-04T19:53:45+08:00"
  },
  {
    "id": "1783160537000-20260704_ma4.webp",
    "filename": "20260704_ma4.webp",
    "url": "https://pico-beige.vercel.app/api/image?path=sd/20260704_ma4.webp",
    "folder": "sd",
    "time": "2026-07-04T18:22:17+08:00"
  },
  {
    "id": "1783160535000-20260704_ma3.webp",
    "filename": "20260704_ma3.webp",
    "url": "https://pico-beige.vercel.app/api/image?path=sd/20260704_ma3.webp",
    "folder": "sd",
    "time": "2026-07-04T18:22:15+08:00"
  },
  {
    "id": "1783160532000-20260704_ma2.webp",
    "filename": "20260704_ma2.webp",
    "url": "https://pico-beige.vercel.app/api/image?path=sd/20260704_ma2.webp",
    "folder": "sd",
    "time": "2026-07-04T18:22:12+08:00"
  },
  {
    "id": "1783160530000-20260704_ma1.webp",
    "filename": "20260704_ma1.webp",
    "url": "https://pico-beige.vercel.app/api/image?path=sd/20260704_ma1.webp",
    "folder": "sd",
    "time": "2026-07-04T18:22:10+08:00"
  },
  {
    "id": "1783143022000-20260704_195.webp",
    "filename": "20260704_195.webp",
    "url": "https://pico-beige.vercel.app/api/image?path=cover/20260704_195.webp",
    "folder": "cover",
    "time": "2026-07-04T13:30:22+08:00"
  },
  {
    "id": "1783132482000-20260704_huansan.webp",
    "filename": "20260704_huansan.webp",
    "url": "https://pico-beige.vercel.app/api/image?path=sd/20260704_huansan.webp",
    "folder": "sd",
    "time": "2026-07-04T10:34:42+08:00"
  },
  {
    "id": "1783056393000-20260703_ait1.jpg",
    "filename": "20260703_ait1.jpg",
    "url": "https://pico-beige.vercel.app/api/image?path=wallpaper/20260703_ait1.jpg",
    "folder": "wallpaper",
    "time": "2026-07-03T13:26:33+08:00"
  },
  {
    "id": "1782995792000-20260702_fj53.webp",
    "filename": "20260702_fj53.webp",
    "url": "https://pico-beige.vercel.app/api/image?path=wallpaper/20260702_fj53.webp",
    "folder": "wallpaper",
    "time": "2026-07-02T20:36:32+08:00"
  },
  {
    "id": "1782995035000-20260702_cf01.webp",
    "filename": "20260702_cf01.webp",
    "url": "https://pico-beige.vercel.app/api/image?path=cover/20260702_cf01.webp",
    "folder": "cover",
    "time": "2026-07-02T20:23:55+08:00"
  },
  {
    "id": "1782988840000-20260702_sh1.webp",
    "filename": "20260702_sh1.webp",
    "url": "https://pico-beige.vercel.app/api/image?path=wallpaper/20260702_sh1.webp",
    "folder": "wallpaper",
    "time": "2026-07-02T18:40:40+08:00"
  },
  {
    "id": "1782973389000-20260702_bz23.jpg",
    "filename": "20260702_bz23.jpg",
    "url": "https://pico-beige.vercel.app/api/image?path=wallpaper/20260702_bz23.jpg",
    "folder": "wallpaper",
    "time": "2026-07-02T14:23:09+08:00"
  },
  {
    "id": "1782972282000-20260702_bz9.jpg",
    "filename": "20260702_bz9.jpg",
    "url": "https://pico-beige.vercel.app/api/image?path=sd/20260702_bz9.jpg",
    "folder": "sd",
    "time": "2026-07-02T14:04:42+08:00"
  },
  {
    "id": "1782966298000-20260702_bz22.webp",
    "filename": "20260702_bz22.webp",
    "url": "https://pico-beige.vercel.app/api/image?path=wallpaper/20260702_bz22.webp",
    "folder": "wallpaper",
    "time": "2026-07-02T12:24:58+08:00"
  },
  {
    "id": "1782914142000-20260701_by4.webp",
    "filename": "20260701_by4.webp",
    "url": "https://pico-beige.vercel.app/api/image?path=wallpaper/20260701_by4.webp",
    "folder": "wallpaper",
    "time": "2026-07-01T21:55:42+08:00"
  },
  {
    "id": "1782907985000-20260701_bz5.webp",
    "filename": "20260701_bz5.webp",
    "url": "https://pico-beige.vercel.app/api/image?path=wallpaper/20260701_bz5.webp",
    "folder": "wallpaper",
    "time": "2026-07-01T20:13:05+08:00"
  },
  {
    "id": "1782903035000-20260701_bz22.jpg",
    "filename": "20260701_bz22.jpg",
    "url": "https://pico-beige.vercel.app/api/image?path=wallpaper/20260701_bz22.jpg",
    "folder": "wallpaper",
    "time": "2026-07-01T18:50:35+08:00"
  },
  {
    "id": "1782902938000-20260701_m1__3_.webp",
    "filename": "20260701_m1__3_.webp",
    "url": "https://pico-beige.vercel.app/api/image?path=wallpaper/20260701_m1__3_.webp",
    "folder": "wallpaper",
    "time": "2026-07-01T18:48:58+08:00"
  },
  {
    "id": "1782902678000-20260701_m1__8_.jpg",
    "filename": "20260701_m1__8_.jpg",
    "url": "https://pico-beige.vercel.app/api/image?path=wallpaper/20260701_m1__8_.jpg",
    "folder": "wallpaper",
    "time": "2026-07-01T18:44:38+08:00"
  },
  {
    "id": "1782902630000-20260701_bz21.jpg",
    "filename": "20260701_bz21.jpg",
    "url": "https://pico-beige.vercel.app/api/image?path=wallpaper/20260701_bz21.jpg",
    "folder": "wallpaper",
    "time": "2026-07-01T18:43:50+08:00"
  },
  {
    "id": "1782901752000-20260701_m1.jpg",
    "filename": "20260701_m1.jpg",
    "url": "https://pico-beige.vercel.app/api/image?path=wallpaper/20260701_m1.jpg",
    "folder": "wallpaper",
    "time": "2026-07-01T18:29:12+08:00"
  },
  {
    "id": "1782878666000-20260701_bj21.jpg",
    "filename": "20260701_bj21.jpg",
    "url": "https://pico-beige.vercel.app/api/image?path=wallpaper/20260701_bj21.jpg",
    "folder": "wallpaper",
    "time": "2026-07-01T12:04:26+08:00"
  },
  {
    "id": "1782873441000-20260701_412.webp",
    "filename": "20260701_412.webp",
    "url": "https://pico-beige.vercel.app/api/image?path=wallpaper/20260701_412.webp",
    "folder": "wallpaper",
    "time": "2026-07-01T10:37:21+08:00"
  },
  {
    "id": "1782869675000-20260701_147877.jpg",
    "filename": "20260701_147877.jpg",
    "url": "https://pico-beige.vercel.app/api/image?path=wallpaper/20260701_147877.jpg",
    "folder": "wallpaper",
    "time": "2026-07-01T09:34:35+08:00"
  },
  {
    "id": 1782864117158,
    "filename": "20260701_bj19.webp",
    "url": "https://pico.1356666.xyz/api/image?path=wallpaper/20260701_bj19.webp",
    "folder": "wallpaper",
    "time": "2026-07-01T00:01:57.158Z"
  },
  {
    "id": 1782864010455,
    "filename": "20260701_background.webp",
    "url": "https://pico.1356666.xyz/api/image?path=telegram/stickers%2Ffile_57.webp",
    "folder": "wallpaper",
    "time": "2026-07-01T00:00:10.455Z"
  },
  {
    "id": 1782819988478,
    "filename": "20260630_mb__8_.jpg",
    "url": "https://pico.1356666.xyz/api/image?path=wallpaper/20260630_mb__8_.jpg",
    "folder": "wallpaper",
    "time": "2026-06-30T11:46:28.478Z"
  },
  {
    "id": 1782814755709,
    "filename": "20260630_bonsai-2202769.jpg",
    "url": "https://pico.1356666.xyz/api/image?path=telegram/photos%2Ffile_47.jpg",
    "folder": "wallpaper",
    "time": "2026-06-30T10:19:15.709Z"
  },
  {
    "id": 1782807480812,
    "filename": "20260630_bj22.jpg",
    "url": "https://pico.1356666.xyz/api/image?path=telegram/photos%2Ffile_46.jpg",
    "folder": "wallpaper",
    "time": "2026-06-30T08:18:00.812Z"
  },
  {
    "id": 1782807318073,
    "filename": "20260630_bj9.jpg",
    "url": "https://pico.1356666.xyz/api/image?path=wallpaper/20260630_bj9.jpg",
    "folder": "wallpaper",
    "time": "2026-06-30T08:15:18.073Z"
  },
  {
    "id": 1782806651599,
    "filename": "20260630_fj2.jpg",
    "url": "https://pico.1356666.xyz/api/image?path=wallpaper/20260630_fj2.jpg",
    "folder": "wallpaper",
    "time": "2026-06-30T08:04:11.599Z"
  },
  {
    "id": 1782806604002,
    "filename": "20260630_by1.jpg",
    "url": "https://pico.1356666.xyz/api/image?path=wallpaper/20260630_by1.jpg",
    "folder": "wallpaper",
    "time": "2026-06-30T08:03:24.002Z"
  },
  {
    "id": 1782801539265,
    "filename": "20260630_by2.jpg",
    "url": "https://pico.1356666.xyz/api/image?path=wallpaper/20260630_by2.jpg",
    "folder": "wallpaper",
    "time": "2026-06-30T06:38:59.265Z"
  },
  {
    "id": 1782801188842,
    "filename": "20260630_fj10.jpg",
    "url": "https://pico.1356666.xyz/api/image?path=wallpaper/20260630_fj10.jpg",
    "folder": "wallpaper",
    "time": "2026-06-30T06:33:08.842Z"
  },
  {
    "id": 1782800888163,
    "filename": "20260630_bj27.jpg",
    "url": "https://pico.1356666.xyz/api/image?path=wallpaper/20260630_bj27.jpg",
    "folder": "wallpaper",
    "time": "2026-06-30T06:28:08.163Z"
  },
  {
    "id": 1782800419347,
    "filename": "20260630_image.jpg",
    "url": "https://pico.1356666.xyz/api/image?path=telegram/photos%2Ffile_45.jpg",
    "folder": "wallpaper",
    "time": "2026-06-30T06:20:19.347Z"
  },
  {
    "id": 1782800362755,
    "filename": "20260630_fj92.jpg",
    "url": "https://pico.1356666.xyz/api/image?path=telegram/photos%2Ffile_44.jpg",
    "folder": "wallpaper",
    "time": "2026-06-30T06:19:22.755Z"
  },
  {
    "id": 1782799857088,
    "filename": "20260630_city1.webp",
    "url": "https://pico.1356666.xyz/api/image?path=wallpaper/20260630_city1.webp",
    "folder": "wallpaper",
    "time": "2026-06-30T06:10:57.088Z"
  },
  {
    "id": 1782799610862,
    "filename": "20260630_843e7eef7ad6017a4888d7869e27efea.jpg",
    "url": "https://pico.1356666.xyz/api/image?path=telegram/photos%2Ffile_43.jpg",
    "folder": "wallpaper",
    "time": "2026-06-30T06:06:50.862Z"
  },
  {
    "id": 1782726543663,
    "filename": "20260629_bz4.webp",
    "url": "https://pico.1356666.xyz/api/image?path=telegram/stickers%2Ffile_42.webp",
    "folder": "wallpaper",
    "time": "2026-06-29T09:49:03.663Z"
  },
  {
    "id": 1782726534922,
    "filename": "20260629_bz2.webp",
    "url": "https://pico.1356666.xyz/api/image?path=telegram/stickers%2Ffile_41.webp",
    "folder": "wallpaper",
    "time": "2026-06-29T09:48:54.922Z"
  },
  {
    "id": 1782726527868,
    "filename": "20260629_bz1.webp",
    "url": "https://pico.1356666.xyz/api/image?path=telegram/stickers%2Ffile_40.webp",
    "folder": "wallpaper",
    "time": "2026-06-29T09:48:47.868Z"
  },
  {
    "id": 1782721346065,
    "filename": "20260629_sz2.jpg",
    "url": "https://pico.1356666.xyz/api/image?path=telegram/photos%2Ffile_39.jpg",
    "folder": "wallpaper",
    "time": "2026-06-29T08:22:26.065Z"
  },
  {
    "id": 1782720346078,
    "filename": "20260629_bj27.jpg",
    "url": "https://pico.1356666.xyz/api/image?path=telegram/photos%2Ffile_38.jpg",
    "folder": "wallpaper",
    "time": "2026-06-29T08:05:46.078Z"
  },
  {
    "id": 1782468633718,
    "filename": "20260626_bz4.jpg",
    "url": "https://pico.1356666.xyz/api/image?path=telegram/photos%2Ffile_37.jpg",
    "folder": "wallpaper",
    "time": "2026-06-26T10:10:33.718Z"
  },
  {
    "id": 1782468625367,
    "filename": "20260626_bz2.jpg",
    "url": "https://pico.1356666.xyz/api/image?path=telegram/photos%2Ffile_36.jpg",
    "folder": "wallpaper",
    "time": "2026-06-26T10:10:25.367Z"
  },
  {
    "id": 1782468617216,
    "filename": "20260626_bz1.jpg",
    "url": "https://pico.1356666.xyz/api/image?path=telegram/photos%2Ffile_35.jpg",
    "folder": "wallpaper",
    "time": "2026-06-26T10:10:17.216Z"
  },
  {
    "id": 1782468610216,
    "filename": "20260626_ait1.jpg",
    "url": "https://pico.1356666.xyz/api/image?path=telegram/photos%2Ffile_34.jpg",
    "folder": "wallpaper",
    "time": "2026-06-26T10:10:10.216Z"
  },
  {
    "id": 1782468604700,
    "filename": "20260626_147877.jpg",
    "url": "https://pico.1356666.xyz/api/image?path=telegram/photos%2Ffile_33.jpg",
    "folder": "wallpaper",
    "time": "2026-06-26T10:10:04.700Z"
  },
  {
    "id": 1782461232509,
    "filename": "20260626_00e51ee7bf8b0dc06963e82c818b0e50.jpg",
    "url": "https://pico.1356666.xyz/api/image?path=telegram/photos%2Ffile_32.jpg",
    "folder": "wallpaper",
    "time": "2026-06-26T08:07:12.509Z"
  },
  {
    "id": 1782366566632,
    "filename": "20260625_building.webp",
    "url": "https://pico.1356666.xyz/api/image?path=wallpaper/20260625_building.webp",
    "folder": "wallpaper",
    "time": "2026-06-25T05:49:26.632Z"
  },
  {
    "id": 1782195454103,
    "filename": "20260623_bz34.webp",
    "url": "https://pico.1356666.xyz/api/image?path=telegram/stickers%2Ffile_31.webp",
    "folder": "wallpaper",
    "time": "2026-06-23T06:17:34.103Z"
  },
  {
    "id": 1782195448120,
    "filename": "20260623_bz32.webp",
    "url": "https://pico.1356666.xyz/api/image?path=telegram/stickers%2Ffile_30.webp",
    "folder": "wallpaper",
    "time": "2026-06-23T06:17:28.120Z"
  },
  {
    "id": 1782195442548,
    "filename": "20260623_bz31.webp",
    "url": "https://pico.1356666.xyz/api/image?path=telegram/stickers%2Ffile_29.webp",
    "folder": "wallpaper",
    "time": "2026-06-23T06:17:22.548Z"
  },
  {
    "id": 1782195436817,
    "filename": "20260623_bz30.webp",
    "url": "https://pico.1356666.xyz/api/image?path=telegram/stickers%2Ffile_28.webp",
    "folder": "wallpaper",
    "time": "2026-06-23T06:17:16.817Z"
  },
  {
    "id": 1782195430231,
    "filename": "20260623_bz29.webp",
    "url": "https://pico.1356666.xyz/api/image?path=telegram/stickers%2Ffile_27.webp",
    "folder": "wallpaper",
    "time": "2026-06-23T06:17:10.231Z"
  },
  {
    "id": 1782195424671,
    "filename": "20260623_bz27.webp",
    "url": "https://pico.1356666.xyz/api/image?path=telegram/stickers%2Ffile_26.webp",
    "folder": "wallpaper",
    "time": "2026-06-23T06:17:04.671Z"
  },
  {
    "id": 1782195418034,
    "filename": "20260623_bz25.webp",
    "url": "https://pico.1356666.xyz/api/image?path=telegram/stickers%2Ffile_25.webp",
    "folder": "wallpaper",
    "time": "2026-06-23T06:16:58.034Z"
  },
  {
    "id": 1782195412343,
    "filename": "20260623_bz24.webp",
    "url": "https://pico.1356666.xyz/api/image?path=telegram/stickers%2Ffile_24.webp",
    "folder": "wallpaper",
    "time": "2026-06-23T06:16:52.343Z"
  },
  {
    "id": 1782195405918,
    "filename": "20260623_bz23.webp",
    "url": "https://pico.1356666.xyz/api/image?path=telegram/stickers%2Ffile_23.webp",
    "folder": "wallpaper",
    "time": "2026-06-23T06:16:45.918Z"
  },
  {
    "id": 1782195400342,
    "filename": "20260623_bz20.webp",
    "url": "https://pico.1356666.xyz/api/image?path=telegram/stickers%2Ffile_22.webp",
    "folder": "wallpaper",
    "time": "2026-06-23T06:16:40.342Z"
  },
  {
    "id": 1782195394666,
    "filename": "20260623_bz6.webp",
    "url": "https://pico.1356666.xyz/api/image?path=telegram/stickers%2Ffile_21.webp",
    "folder": "wallpaper",
    "time": "2026-06-23T06:16:34.666Z"
  },
  {
    "id": 1782195388670,
    "filename": "20260623_bz5.webp",
    "url": "https://pico.1356666.xyz/api/image?path=telegram/stickers%2Ffile_20.webp",
    "folder": "wallpaper",
    "time": "2026-06-23T06:16:28.670Z"
  },
  {
    "id": 1782195383120,
    "filename": "20260623_bz4.webp",
    "url": "https://pico.1356666.xyz/api/image?path=telegram/stickers%2Ffile_19.webp",
    "folder": "wallpaper",
    "time": "2026-06-23T06:16:23.120Z"
  },
  {
    "id": 1782195376062,
    "filename": "20260623_bz3.webp",
    "url": "https://pico.1356666.xyz/api/image?path=telegram/stickers%2Ffile_18.webp",
    "folder": "wallpaper",
    "time": "2026-06-23T06:16:16.062Z"
  },
  {
    "id": 1782183721893,
    "filename": "20260623_map3__1_.jpg",
    "url": "https://pico.1356666.xyz/api/image?path=wallpaper/20260623_map3__1_.jpg",
    "folder": "wallpaper",
    "time": "2026-06-23T03:02:01.893Z"
  },
  {
    "id": 1782182817086,
    "filename": "20260623_bj26.webp",
    "url": "https://pico.1356666.xyz/api/image?path=telegram/stickers%2Ffile_17.webp",
    "folder": "wallpaper",
    "time": "2026-06-23T02:46:57.086Z"
  },
  {
    "id": 1782179126080,
    "filename": "20260623_fj52.webp",
    "url": "https://pico.1356666.xyz/api/image?path=telegram/documents%2Ffile_16.webp",
    "folder": "wallpaper",
    "time": "2026-06-23T01:45:26.080Z"
  },
  {
    "id": 1782178955924,
    "filename": "20260623_bz2.webp",
    "url": "https://pico.1356666.xyz/api/image?path=telegram/stickers%2Ffile_15.webp",
    "folder": "wallpaper",
    "time": "2026-06-23T01:42:35.924Z"
  },
  {
    "id": 1782178584860,
    "filename": "20260623_bz1.jpg",
    "url": "https://pico.1356666.xyz/api/image?path=telegram/photos%2Ffile_14.jpg",
    "folder": "wallpaper",
    "time": "2026-06-23T01:36:24.860Z"
  },
  {
    "id": 1782174364590,
    "filename": "20260623_fj55.webp",
    "url": "https://pico.1356666.xyz/api/image?path=telegram/documents%2Ffile_13.webp",
    "folder": "wallpaper",
    "time": "2026-06-23T00:26:04.590Z"
  },
  {
    "id": 1782174307433,
    "filename": "20260623_map3__3_.jpg",
    "url": "https://pico.1356666.xyz/api/image?path=wallpaper/20260623_map3__3_.jpg",
    "folder": "wallpaper",
    "time": "2026-06-23T00:25:07.433Z"
  },
  {
    "id": 1782173595445,
    "filename": "20260623_image.webp",
    "url": "https://pico.1356666.xyz/api/image?path=telegram/documents%2Ffile_12.webp",
    "folder": "wallpaper",
    "time": "2026-06-23T00:13:15.445Z"
  },
  {
    "id": 1782173442141,
    "filename": "20260623_map3__3_.webp",
    "url": "https://pico.1356666.xyz/api/image?path=telegram/stickers%2Ffile_11.webp",
    "folder": "wallpaper",
    "time": "2026-06-23T00:10:42.141Z"
  },
  {
    "id": 1782172583390,
    "filename": "20260622_by2.jpg",
    "url": "https://pico.1356666.xyz/api/image?path=telegram/photos%2Ffile_10.jpg",
    "folder": "wallpaper",
    "time": "2026-06-22T23:56:23.390Z"
  },
  {
    "id": 1782172477953,
    "filename": "20260622_fj6.jpg",
    "url": "https://pico.1356666.xyz/api/image?path=telegram/photos%2Ffile_9.jpg",
    "folder": "wallpaper",
    "time": "2026-06-22T23:54:37.953Z"
  },
  {
    "id": 1782172244706,
    "filename": "20260622_by1.jpg",
    "url": "https://pico.1356666.xyz/api/image?path=telegram/photos%2Ffile_8.jpg",
    "folder": "wallpaper",
    "time": "2026-06-22T23:50:44.706Z"
  },
  {
    "id": 1782171066099,
    "filename": "20260622_by5.jpg",
    "url": "https://pico.1356666.xyz/api/image?path=telegram/documents%2Ffile_7.jpg",
    "folder": "wallpaper",
    "time": "2026-06-22T23:31:06.099Z"
  },
  {
    "id": 1782171016653,
    "filename": "20260622_ait1.jpg",
    "url": "https://pico.1356666.xyz/api/image?path=telegram/documents%2Ffile_6.jpg",
    "folder": "sh",
    "time": "2026-06-22T23:30:16.653Z"
  },
  {
    "id": 1782170938726,
    "filename": "20260622_bj19.webp",
    "url": "https://pico.1356666.xyz/api/image?path=telegram/documents%2Ffile_5.webp",
    "folder": "wallpaper",
    "time": "2026-06-22T23:28:58.726Z"
  },
  {
    "id": 1782170897635,
    "filename": "20260622_bz1.jpg",
    "url": "https://pico.1356666.xyz/api/image?path=telegram/documents%2Ffile_4.jpg",
    "folder": "wallpaper",
    "time": "2026-06-22T23:28:17.635Z"
  },
  {
    "id": 1782139402200,
    "filename": "20260622_hao1.jpeg",
    "url": "https://pico.1356666.xyz/api/image?path=telegram/documents%2Ffile_3.jpeg",
    "folder": "wallpaper",
    "time": "2026-06-22T14:43:22.200Z"
  },
  {
    "id": 1782138859524,
    "filename": "20260622_bj1.jpg",
    "url": "https://pico.1356666.xyz/api/image?path=wallpaper/20260622_bj1.jpg",
    "folder": "wallpaper",
    "time": "2026-06-22T14:34:19.524Z"
  },
  {
    "id": 1782138568005,
    "filename": "20260622_fg88.webp",
    "url": "https://pico.1356666.xyz/api/image?path=wallpaper/20260622_fg88.webp",
    "folder": "wallpaper",
    "time": "2026-06-22T14:29:28.005Z"
  },
  {
    "id": 1782138245608,
    "filename": "20260622_bb02.jpg",
    "url": "https://pico.1356666.xyz/api/image?path=wallpaper/20260622_bb02.jpg",
    "folder": "wallpaper",
    "time": "2026-06-22T14:24:05.608Z"
  },
  {
    "id": 1782094393065,
    "filename": "20260622_bz34.webp",
    "url": "https://pico.1356666.xyz/api/image?path=wallpaper/20260622_bz34.webp",
    "folder": "wallpaper",
    "time": "2026-06-22T02:13:13.065Z"
  },
  {
    "id": 1782094389000,
    "filename": "20260622_bz30.webp",
    "url": "https://pico.1356666.xyz/api/image?path=wallpaper/20260622_bz30.webp",
    "folder": "wallpaper",
    "time": "2026-06-22T02:13:09.000Z"
  },
  {
    "id": 1782094384688,
    "filename": "20260622_bz26.webp",
    "url": "https://pico.1356666.xyz/api/image?path=wallpaper/20260622_bz26.webp",
    "folder": "wallpaper",
    "time": "2026-06-22T02:13:04.688Z"
  },
  {
    "id": 1782094380811,
    "filename": "20260622_bz5.webp",
    "url": "https://pico.1356666.xyz/api/image?path=wallpaper/20260622_bz5.webp",
    "folder": "wallpaper",
    "time": "2026-06-22T02:13:00.811Z"
  },
  {
    "id": 1782094377350,
    "filename": "20260622_bz3.webp",
    "url": "https://pico.1356666.xyz/api/image?path=wallpaper/20260622_bz3.webp",
    "folder": "wallpaper",
    "time": "2026-06-22T02:12:57.350Z"
  },
  {
    "id": 1781862694968,
    "filename": "20260619_bj3.webp",
    "url": "https://pico.1356666.xyz/api/image?path=wallpaper/20260619_bj3.webp",
    "folder": "wallpaper",
    "time": "2026-06-19T09:51:34.968Z"
  },
  {
    "id": 1781676395597,
    "filename": "20260617_412.webp",
    "url": "https://pico.1356666.xyz/api/image?path=wallpaper/20260617_412.webp",
    "folder": "wallpaper",
    "time": "2026-06-17T06:06:35.597Z"
  },
  {
    "id": 1781676345698,
    "filename": "20260617_fj3.jpg",
    "url": "https://pico.1356666.xyz/api/image?path=cover/20260617_fj3.jpg",
    "folder": "cover",
    "time": "2026-06-17T06:05:45.698Z"
  },
  {
    "id": 1781676299108,
    "filename": "20260617_fj2.jpg",
    "url": "https://pico.1356666.xyz/api/image?path=sh/20260617_fj2.jpg",
    "folder": "sh",
    "time": "2026-06-17T06:04:59.108Z"
  },
  {
    "id": 1781676270421,
    "filename": "20260617_fj1.jpg",
    "url": "https://pico.1356666.xyz/api/image?path=sd/20260617_fj1.jpg",
    "folder": "sd",
    "time": "2026-06-17T06:04:30.421Z"
  },
  {
    "id": 1781676206864,
    "filename": "20260617_412.webp",
    "url": "https://pico.1356666.xyz/api/image?path=sd/20260617_412.webp",
    "folder": "sd",
    "time": "2026-06-17T06:03:26.864Z"
  },
  {
    "id": 1781676181813,
    "filename": "20260617_fj3.jpg",
    "url": "https://pico.1356666.xyz/api/image?path=sh/20260617_fj3.jpg",
    "folder": "sh",
    "time": "2026-06-17T06:03:01.813Z"
  },
  {
    "id": 1781676150229,
    "filename": "20260617_fj2.jpg",
    "url": "https://pico.1356666.xyz/api/image?path=cover/20260617_fj2.jpg",
    "folder": "cover",
    "time": "2026-06-17T06:02:30.229Z"
  },
  {
    "id": 1781676109484,
    "filename": "20260617_fj1.jpg",
    "url": "https://pico.1356666.xyz/api/image?path=wallpaper/20260617_fj1.jpg",
    "folder": "wallpaper",
    "time": "2026-06-17T06:01:49.484Z"
  },
  {
    "id": 1781671285083,
    "filename": "20260617_204.webp",
    "url": "https://pico.1356666.xyz/api/image?path=wallpaper/20260617_204.webp",
    "folder": "wallpaper",
    "time": "2026-06-17T04:41:25.083Z"
  },
  {
    "id": 1781670129134,
    "filename": "20260617_206.webp",
    "url": "https://pico.1356666.xyz/api/image?path=wallpaper/20260617_206.webp",
    "folder": "wallpaper",
    "time": "2026-06-17T04:22:09.134Z"
  },
  {
    "id": 1781668690038,
    "filename": "20260617_cover.jpg",
    "url": "https://pico.1356666.xyz/api/image?path=wallpaper/20260617_cover.jpg",
    "folder": "wallpaper",
    "time": "2026-06-17T03:58:10.038Z"
  },
  {
    "id": 1781668457516,
    "filename": "20260617_fj55.jpg",
    "url": "https://pico.1356666.xyz/api/image?path=sd/20260617_fj55.jpg",
    "folder": "sd",
    "time": "2026-06-17T03:54:17.516Z"
  },
  {
    "id": 1781668440133,
    "filename": "20260617_fj54.jpg",
    "url": "https://pico.1356666.xyz/api/image?path=sd/20260617_fj54.jpg",
    "folder": "sd",
    "time": "2026-06-17T03:54:00.133Z"
  },
  {
    "id": 1781622321908,
    "filename": "20260616_mmexport1776826256594.webp",
    "url": "https://pico.1356666.xyz/api/image?path=wallpaper/20260616_mmexport1776826256594.webp",
    "folder": "wallpaper",
    "time": "2026-06-16T15:05:21.908Z"
  },
  {
    "id": 1781621211067,
    "filename": "20260616_9D9A1330.webp",
    "url": "https://pico.1356666.xyz/api/image?path=sh/20260616_9D9A1330.webp",
    "folder": "sh",
    "time": "2026-06-16T14:46:51.067Z"
  },
  {
    "id": 1781620082334,
    "filename": "20260616_HIWuTLZbgAAY7sX.jpg",
    "url": "https://cf-pico.pages.dev/api/image?path=wallpaper/20260616_HIWuTLZbgAAY7sX.jpg",
    "folder": "wallpaper",
    "time": "2026-06-16T14:28:02.334Z"
  },
  {
    "id": 1781619289943,
    "filename": "20260616_69ac1b23a85ab.png",
    "url": "https://cf-pico.pages.dev/api/image?path=wallpaper/20260616_69ac1b23a85ab.png",
    "folder": "wallpaper",
    "time": "2026-06-16T14:14:49.943Z"
  },
  {
    "id": 1781618513358,
    "filename": "20260616_sh1.jpg",
    "url": "https://cf-pico.pages.dev/api/image?path=wallpaper/20260616_sh1.jpg",
    "folder": "wallpaper",
    "time": "2026-06-16T14:01:53.358Z"
  },
  {
    "id": "1781574410000-20260616_fj6.jpg",
    "filename": "20260616_fj6.jpg",
    "url": "https://pico-beige.vercel.app/api/image?path=wallpaper/20260616_fj6.jpg",
    "folder": "wallpaper",
    "time": "2026-06-16T09:46:50+08:00"
  },
  {
    "id": "1781572983000-random2.webp",
    "filename": "random2.webp",
    "url": "https://pico-beige.vercel.app/api/image?path=cover/random2.webp",
    "folder": "cover",
    "time": "2026-06-16T09:23:03+08:00"
  },
  {
    "id": "1781525147000-mmexport1744081790643.jpg",
    "filename": "mmexport1744081790643.jpg",
    "url": "https://pico-beige.vercel.app/api/image?path=sd/mmexport1744081790643.jpg",
    "folder": "sd",
    "time": "2026-06-15T20:05:47+08:00"
  },
  {
    "id": "1781523841000-IMG_5500-opq4524590508.jpg",
    "filename": "IMG_5500-opq4524590508.jpg",
    "url": "https://pico-beige.vercel.app/api/image?path=sh/IMG_5500-opq4524590508.jpg",
    "folder": "sh",
    "time": "2026-06-15T19:44:01+08:00"
  },
  {
    "id": "1781517491000-20260615_IMG_5790-opq4528121301.jpg",
    "filename": "20260615_IMG_5790-opq4528121301.jpg",
    "url": "https://pico-beige.vercel.app/api/image?path=sh/20260615_IMG_5790-opq4528121301.jpg",
    "folder": "sh",
    "time": "2026-06-15T17:58:11+08:00"
  },
  {
    "id": "1781517411000-20260615_IMG_20260425_092503.jpg",
    "filename": "20260615_IMG_20260425_092503.jpg",
    "url": "https://pico-beige.vercel.app/api/image?path=sd/20260615_IMG_20260425_092503.jpg",
    "folder": "sd",
    "time": "2026-06-15T17:56:51+08:00"
  },
  {
    "id": "1781512395000-mmexport1774233537614.jpg",
    "filename": "mmexport1774233537614.jpg",
    "url": "https://pico-beige.vercel.app/api/image?path=sd/mmexport1774233537614.jpg",
    "folder": "sd",
    "time": "2026-06-15T16:33:15+08:00"
  },
  {
    "id": "1781505770000-20260615_mmexport1757030460321.jpg",
    "filename": "20260615_mmexport1757030460321.jpg",
    "url": "https://pico-beige.vercel.app/api/image?path=sh/20260615_mmexport1757030460321.jpg",
    "folder": "sh",
    "time": "2026-06-15T14:42:50+08:00"
  },
  {
    "id": "1781503428000-20260615_mmexport1748605601443.jpg",
    "filename": "20260615_mmexport1748605601443.jpg",
    "url": "https://pico-beige.vercel.app/api/image?path=sd/20260615_mmexport1748605601443.jpg",
    "folder": "sd",
    "time": "2026-06-15T14:03:48+08:00"
  },
  {
    "id": "1781503406000-20260615_mmexport1748605598266.jpg",
    "filename": "20260615_mmexport1748605598266.jpg",
    "url": "https://pico-beige.vercel.app/api/image?path=sh/20260615_mmexport1748605598266.jpg",
    "folder": "sh",
    "time": "2026-06-15T14:03:26+08:00"
  },
  {
    "id": "1781498448000-20260615_random3.webp",
    "filename": "20260615_random3.webp",
    "url": "https://pico-beige.vercel.app/api/image?path=wallpaper/20260615_random3.webp",
    "folder": "wallpaper",
    "time": "2026-06-15T12:40:48+08:00"
  },
  {
    "id": "1781496383000-20260615_image.jpg",
    "filename": "20260615_image.jpg",
    "url": "https://pico-beige.vercel.app/api/image?path=wallpaper/20260615_image.jpg",
    "folder": "wallpaper",
    "time": "2026-06-15T12:06:23+08:00"
  },
  {
    "id": "1781492574000-206.webp",
    "filename": "206.webp",
    "url": "https://pico-beige.vercel.app/api/image?path=wallpaper/206.webp",
    "folder": "wallpaper",
    "time": "2026-06-15T11:02:54+08:00"
  }
]